hello/__init__.py
hello/core.py
hello_fiap-1.0.0.dist-info/METADATA
hello_fiap-1.0.0.dist-info/WHEEL
hello_fiap-1.0.0.dist-info/top_level.txt
hello_fiap-1.0.0.dist-info/RECORD
